odoo/addons/stock_move_reset_quantity/README.rst
odoo/addons/stock_move_reset_quantity/__init__.py
odoo/addons/stock_move_reset_quantity/__manifest__.py
odoo/addons/stock_move_reset_quantity/i18n/it.po
odoo/addons/stock_move_reset_quantity/i18n/stock_move_reset_quantity.pot
odoo/addons/stock_move_reset_quantity/models/__init__.py
odoo/addons/stock_move_reset_quantity/models/stock_move_line.py
odoo/addons/stock_move_reset_quantity/models/stock_picking.py
odoo/addons/stock_move_reset_quantity/readme/CONTRIBUTORS.md
odoo/addons/stock_move_reset_quantity/readme/DESCRIPTION.md
odoo/addons/stock_move_reset_quantity/static/description/icon.png
odoo/addons/stock_move_reset_quantity/static/description/index.html
odoo/addons/stock_move_reset_quantity/tests/__init__.py
odoo/addons/stock_move_reset_quantity/tests/test_reset_quantity.py
odoo/addons/stock_move_reset_quantity/views/stock_move_line.xml
odoo/addons/stock_move_reset_quantity/views/stock_picking.xml
odoo_addon_stock_move_reset_quantity-18.0.1.0.0.4.dist-info/METADATA
odoo_addon_stock_move_reset_quantity-18.0.1.0.0.4.dist-info/WHEEL
odoo_addon_stock_move_reset_quantity-18.0.1.0.0.4.dist-info/top_level.txt
odoo_addon_stock_move_reset_quantity-18.0.1.0.0.4.dist-info/RECORD
